pystepfunction/__init__.py
pystepfunction/branch.py
pystepfunction/dms.py
pystepfunction/errors.py
pystepfunction/glue.py
pystepfunction/lambda_function.py
pystepfunction/sfn.py
pystepfunction/ssm.py
pystepfunction/state.py
pystepfunction/tasks.py
pystepfunction/viz.py
pystepfunction-1.1.131.dist-info/METADATA
pystepfunction-1.1.131.dist-info/WHEEL
pystepfunction-1.1.131.dist-info/top_level.txt
pystepfunction-1.1.131.dist-info/RECORD
