Metadata-Version: 2.1
Name: pystepfunction
Version: 1.1.131
Summary: Create AWS Step Functions asl.json with Python
Author-email: Chris Hopkinson <therealchrishopkinson@hotmail.com>
Project-URL: Homepage, https://github.com/mrhopko/pystepfunction
Project-URL: Docs, https://mrhopko.github.io/pystepfunction/pystepfunction
Keywords: aws,stepfunctions,step functions
Classifier: License :: OSI Approved :: MIT License
Classifier: Programming Language :: Python
Classifier: Programming Language :: Python :: 3
Requires-Python: >=3.10
Requires-Dist: glom
Requires-Dist: pyvis
Requires-Dist: jsonpath-ng
Requires-Dist: mypy-boto3-dms
Requires-Dist: botocore
Provides-Extra: dev
Requires-Dist: black ; extra == 'dev'
Requires-Dist: pytest ; extra == 'dev'
Requires-Dist: mypy ; extra == 'dev'
